twop_pipeline/TwoPDataPipeline.py
twop_pipeline/__init__.py
twop_pipeline/intan/__init__.py
twop_pipeline/intan/importrhdutilities.py
twop_pipeline/intan/readIntan.py
twop_pipeline/lfp/EMGFromLFP.py
twop_pipeline/lfp/LFPPlots.py
twop_pipeline/lfp/__init__.py
twop_pipeline/lfp/lfpFunctions.py
twop_pipeline/lfp/readLFP.py
twop_pipeline/state/__init__.py
twop_pipeline/state/extractStates.py
twop_pipeline/state/getFacemapData.py
twop_pipeline/state/motionCorrelations.py
twop_pipeline/twop/__init__.py
twop_pipeline/twop/getSuite2POutput.py
twop_pipeline/twop/getTrack2POutput.py
twop_pipeline/twop/plots.py
twop_pipeline/utils/__init__.py
twop_pipeline/utils/alignmentFunctions.py
twop_pipeline/utils/filtering.py
twop_pipeline/utils/getDataFiles.py
twop_pipeline/utils/getFPS.py
twop_pipeline/utils/raw_to_tifs.py
twop_pipeline/utils/stats.py
twop_pipeline-0.1.0.dist-info/METADATA
twop_pipeline-0.1.0.dist-info/WHEEL
twop_pipeline-0.1.0.dist-info/top_level.txt
twop_pipeline-0.1.0.dist-info/RECORD
