Metadata-Version: 2.4
Name: twop_pipeline
Version: 0.1.0
Summary: Two-photon data pipeline utilities
Requires-Python: >=3.9
Requires-Dist: suite2p
Requires-Dist: facemap
Requires-Dist: scipy
Requires-Dist: pandas
Requires-Dist: statsmodels
Requires-Dist: joblib
Requires-Dist: pyarrow
Requires-Dist: lz4
Provides-Extra: ml
Requires-Dist: scikit-learn; extra == "ml"
Provides-Extra: longitudinal
Requires-Dist: track2p; extra == "longitudinal"
Provides-Extra: gpu
Requires-Dist: cupy-cuda12x; platform_system == "Linux" and extra == "gpu"
